listdisk/__init__.py
listdisk/admin.py
listdisk-0.1.0.dist-info/METADATA
listdisk-0.1.0.dist-info/WHEEL
listdisk-0.1.0.dist-info/top_level.txt
listdisk-0.1.0.dist-info/RECORD
